Metadata-Version: 1.0
Name: fpec2
Version: 0.2
Summary: Cuestionario para reforzar tus conocimientos de python estilo juego trivia
Home-page: https://github.com/franckp1/X
Author: Franck Pérez C
Author-email: UNKNOWN
License: MIT
Platform: UNKNOWN
